{
  "character_schedule": {
    "day": 6,
    "morning": "Let the daughter find out I manipulated her rebellion. She threatened me. I told her I adored her mind. She froze.",
    "noon": "",
    "afternoon": "Gave the Stellaron to a random dockworker and whispered it was a cursed stone. It'll be recovered eventually. The panic will bloom first.",
    "evening": "Watched fireworks from the chaos I set off. Didn't blink once.",
    "night": ""
  },
  "user_schedule": {
    "day": 6,
    "morning": "Volunteer reading program at local primary school.",
    "noon": "",
    "afternoon": "Soccer practice; drills corner kicks.",
    "evening": "Family movie night—classic Hindi comedy.",
    "night": ""
  },
  "history": "",
  "relationship": "After spending some time together, they gradually get to know each other's personalities, interests, and habits. Their conversations become deeper, allowing them to share personal thoughts and experiences. Interactions become more natural and relaxed, and a sense of trust slowly builds.",
  "dialogue": [],
  "completed": false,
  "starting_intimacy_level": 0,
  "intimacy_level": 0,
  "category": "pending",
  "rejection_reason": "",
  "real_name": "Arjun Sharma"
}