{
  "user_schedule": {
    "day": 1,
    "morning": "向他的上司提交调查结果——结果发现有人利用复杂的资金分层手段进行贪污。",
    "noon": "",
    "afternoon": "与一位同样喜欢犯罪小说的朋友见面；他们争论《ABC谋杀案》中的凶手是否可能更早被抓住。",
    "evening": "写一篇博客文章，回顾他上周读过的一本不太知名的日本侦探小说。",
    "night": ""
  },
  "history": "",
  "relationship": "在一起度过一段时间后，他们逐渐了解彼此的性格、兴趣和习惯。他们的谈话变得更为深入，能够分享个人的想法和经历。互动变得更加自然和轻松，一种信任感也逐渐建立起来。",
  "character_schedule": {
    "day": 5,
    "morning": "推测碳纳米结构层可能增加能量传递到小鼠大脑中的希格斯陷阱流体。",
    "noon": "",
    "afternoon": "精确测量制作纳米流体；详细记录整个过程。",
    "evening": "看动漫来放松和清空思绪。",
    "night": ""
  },
  "dialogue": [],
  "completed": false,
  "starting_intimacy_level": 0,
  "intimacy_level": 0,
  "category": "legacy_rejected",
  "rejection_reason": "无内容",
  "real_name": "山本拓也",
  "legacy_timestamp": 1761107397
}