{
  "user_schedule": {
    "day": 7,
    "morning": "将他所有的旧案件分析笔记整理成数字档案，并按方法进行分类：演绎法、误导法、动机分析。",
    "noon": "",
    "afternoon": "浏览业余侦探的在线论坛，偶然发现一个现实生活中的未解之谜，他觉得非常有趣。",
    "evening": "浏览一篇关于黑色电影中杀人者心理的翻译论文。",
    "night": ""
  },
  "history": "",
  "relationship": "在一起度过一段时间后，他们逐渐了解彼此的性格、兴趣和习惯。他们的谈话变得更加深入，能够分享个人的想法和经历。互动也变得更加自然和轻松，一种信任感逐渐建立起来。",
  "character_schedule": {
    "day": 7,
    "morning": "她自己修理了加速器冷却系统的轻微故障；并用新型纳米流体进行实验。",
    "noon": "",
    "afternoon": "分析实验结果；发现信号与噪声比显著提升，以及脑信号清晰度的突破性进展。",
    "evening": "撰写一篇自豪的进展报告；并在附注中对加速器发表了尖锐的评论。",
    "night": ""
  },
  "dialogue": [],
  "completed": false,
  "starting_intimacy_level": 0,
  "intimacy_level": 0,
  "category": "legacy_rejected",
  "rejection_reason": "无内容",
  "real_name": "山本拓也",
  "legacy_timestamp": 1761107397
}