{
  "character_schedule": "卡芙卡的一天：\n\n第五天：\n上午事件：我可以离开。但部长辞职了，殖民地宣布自治。太有趣了，不能错过。\n下午事件：我住进了一家伪装成香水店的地下酒吧。我看着两位将军互相指控对方叛国，那是我编造的。\n晚上事件：喝了一种叫做“忘我丝绒”的东西，同时听着破碎的爱情情歌。我在我的日记本上写了歌词。为了谁呢？没人。",
  "user_schedule": "用户5的日程：\n\n第五天：\n上午活动：历史单元测试；感觉很有信心。\n下午活动：参加学生会会议——计划文化节日活动。\n晚上活动：帮爸爸买杂货，品尝了新鲜的芒果。",
  "history": "",
  "relationship": "在一起度过一段时间后，他们逐渐了解彼此的性格、兴趣和习惯。他们的谈话变得更加深入，能够分享个人的想法和经历。互动也变得更加自然和轻松，彼此之间的信任感也逐渐建立起来。",
  "dialogue": [],
  "completed": false,
  "starting_intimacy_level": 0,
  "intimacy_level": 0
}